{
    "list":[
        [{"name":"a","id":"1"}],
        [{"name":"aa","id":"1"},{"name":"bb","id":"2"}],
        [{"name":"aaa","id":"1"},{"name":"bbb","id":"2"},{"name":"ccc","id":"3"}],
        [{"name":"aaaa","id":"1"},{"name":"bbbb","id":"2"},{"name":"cccc","id":"3"},{"name":"dddd","id":"4"}],
        [{"name":"aaaaa","id":"1"},{"name":"bbbbb","id":"2"},{"name":"ccccc","id":"3"},{"name":"ddddd","id":"4"},{"name":"eeeee","id":"5"}],
        [{"name":"aaaaaa","id":"1"},{"name":"bbbbbb","id":"2"},{"name":"cccccc","id":"3"},{"name":"dddddd","id":"4"},{"name":"eeeeee","id":"5"},{"name":"ffffff","id":"6"}],
        [{"name":"aaaaaaa","id":"1"},{"name":"bbbbbbb","id":"2"},{"name":"ccccccc","id":"3"},{"name":"ddddddd","id":"4"},{"name":"eeeeeee","id":"5"},{"name":"fffffff","id":"6"},{"name":"ggggggg","id":"7"}],
        [{"name":"a","id":"1"}],
        [{"name":"aa","id":"1"},{"name":"bb","id":"2"}],
        [{"name":"aaa","id":"1"},{"name":"bbb","id":"2"},{"name":"ccc","id":"3"}],
        [{"name":"aaaa","id":"1"},{"name":"bbbb","id":"2"},{"name":"cccc","id":"3"},{"name":"dddd","id":"4"}],
        [{"name":"aaaaa","id":"1"},{"name":"bbbbb","id":"2"},{"name":"ccccc","id":"3"},{"name":"ddddd","id":"4"},{"name":"eeeee","id":"5"}],
        [{"name":"aaaaaa","id":"1"},{"name":"bbbbbb","id":"2"},{"name":"cccccc","id":"3"},{"name":"dddddd","id":"4"},{"name":"eeeeee","id":"5"},{"name":"ffffff","id":"6"}],
        [{"name":"aaaaaaa","id":"1"},{"name":"bbbbbbb","id":"2"},{"name":"ccccccc","id":"3"},{"name":"ddddddd","id":"4"},{"name":"eeeeeee","id":"5"},{"name":"fffffff","id":"6"},{"name":"ggggggg","id":"7"}]
    ],
    "count":14
}